wis2_aodn_upstream/__init__.py
wis2_aodn_upstream/etl/__init__.py
wis2_aodn_upstream/etl/load.py
wis2_aodn_upstream/etl/transform.py
wis2_aodn_upstream-1.0.0.dist-info/WHEEL
wis2_aodn_upstream-1.0.0.dist-info/METADATA
wis2_aodn_upstream-1.0.0.dist-info/RECORD
