Metadata-Version: 2.3
Name: wis2-aodn-upstream
Version: 1.0.0
Summary: WIS2.0 upstream flow that run on prefect Data Platform to preprocess WIS2 data. 
Requires-Dist: minio>=7.2.16
Requires-Dist: pandas>=2.3.2
Requires-Dist: pre-commit>=4.3.0
Requires-Dist: prefect==3.3.3
Requires-Dist: xarray>=2025.8.0
Requires-Python: >=3.11
